[{"id":"6f8f6cb8.f67314","type":"tab","label":"Twitter API","disabled":false,"info":""},{"id":"6a2d6da.742a994","type":"twitter in","z":"6f8f6cb8.f67314","twitter":"","tags":"food, sports, tech","user":"false","name":"Recibir Twits","inputs":1,"x":230,"y":460,"wires":[["b7cc4601.978888","79f5f02d.784a5","e86d9a9b.281e98"]]},{"id":"b7cc4601.978888","type":"switch","z":"6f8f6cb8.f67314","name":"Filtrar food","property":"payload","propertyType":"msg","rules":[{"t":"cont","v":"food","vt":"str"}],"checkall":"true","repair":false,"outputs":1,"x":470,"y":320,"wires":[["8a37fd2d.b8638","37930ce.7d2eef4"]]},{"id":"79f5f02d.784a5","type":"switch","z":"6f8f6cb8.f67314","name":"Filtrar tech","property":"payload","propertyType":"msg","rules":[{"t":"cont","v":"tech","vt":"str"}],"checkall":"true","repair":false,"outputs":1,"x":470,"y":420,"wires":[["82514ba0.080818","d4614a7e.c48128"]]},{"id":"e86d9a9b.281e98","type":"switch","z":"6f8f6cb8.f67314","name":"Filtrar sports","property":"payload","propertyType":"msg","rules":[{"t":"cont","v":"sports","vt":"str"}],"checkall":"true","repair":false,"outputs":1,"x":470,"y":520,"wires":[["a780877b.991bd8","af809a28.bc1b68"]]},{"id":"8a37fd2d.b8638","type":"change","z":"6f8f6cb8.f67314","name":"food","rules":[{"t":"set","p":"topic","pt":"msg","to":"food","tot":"str"},{"t":"set","p":"payload","pt":"msg","to":"1","tot":"num"}],"action":"","property":"","from":"","to":"","reg":false,"x":670,"y":320,"wires":[["a273486e.d7e328"]]},{"id":"82514ba0.080818","type":"change","z":"6f8f6cb8.f67314","name":"tech","rules":[{"t":"set","p":"topic","pt":"msg","to":"tech","tot":"str"},{"t":"set","p":"payload","pt":"msg","to":"1","tot":"num"}],"action":"","property":"","from":"","to":"","reg":false,"x":670,"y":420,"wires":[["5640b175.392da"]]},{"id":"a780877b.991bd8","type":"change","z":"6f8f6cb8.f67314","name":"sports","rules":[{"t":"set","p":"topic","pt":"msg","to":"sports","tot":"str"},{"t":"set","p":"payload","pt":"msg","to":"1","tot":"num"}],"action":"","property":"","from":"","to":"","reg":false,"x":670,"y":520,"wires":[["d83c9f2e.5cada"]]},{"id":"a273486e.d7e328","type":"function","z":"6f8f6cb8.f67314","name":"Food tracker","func":"var food_op = context.get('food_op') || 0;\nfood_op += 1;\nmsg.payload = food_op;\ncontext.set('food_op',food_op);\nreturn msg;","outputs":1,"noerr":0,"initialize":"","finalize":"","x":870,"y":320,"wires":[["dab012b4.136a6"]]},{"id":"5640b175.392da","type":"function","z":"6f8f6cb8.f67314","name":"tech tracker","func":"var tech_op = context.get('tech_op') || 0;\ntech_op += 1;\nmsg.payload = tech_op;\ncontext.set('tech_op',tech_op);\nreturn msg;","outputs":1,"noerr":0,"initialize":"","finalize":"","x":870,"y":420,"wires":[["dab012b4.136a6"]]},{"id":"d83c9f2e.5cada","type":"function","z":"6f8f6cb8.f67314","name":"sports tracker","func":"var sports_op = context.get('sports_op') || 0;\nsports_op += 1;\nmsg.payload = sports_op;\ncontext.set('sports_op',sports_op);\nreturn msg;","outputs":1,"noerr":0,"initialize":"","finalize":"","x":880,"y":520,"wires":[["dab012b4.136a6"]]},{"id":"37930ce.7d2eef4","type":"ui_text","z":"6f8f6cb8.f67314","group":"6ad9b03.1f9965","order":6,"width":6,"height":1,"name":"food text","label":"Comida","format":"{{msg.payload}}","layout":"col-center","x":700,"y":100,"wires":[]},{"id":"d4614a7e.c48128","type":"ui_text","z":"6f8f6cb8.f67314","group":"6ad9b03.1f9965","order":4,"width":6,"height":1,"name":"tech text","label":"Tecnología","format":"{{msg.payload}}","layout":"col-center","x":700,"y":160,"wires":[]},{"id":"af809a28.bc1b68","type":"ui_text","z":"6f8f6cb8.f67314","group":"6ad9b03.1f9965","order":8,"width":6,"height":1,"name":"sports text","label":"Deportes","format":"{{msg.payload}}","layout":"col-center","x":710,"y":220,"wires":[]},{"id":"dab012b4.136a6","type":"ui_chart","z":"6f8f6cb8.f67314","name":"Grafico","group":"6ad9b03.1f9965","order":13,"width":24,"height":12,"label":"Popularidad de los temas","chartType":"bar","legend":"false","xformat":"HH:mm:ss","interpolate":"linear","nodata":"","dot":false,"ymin":"","ymax":"","removeOlder":1,"removeOlderPoints":"","removeOlderUnit":"3600","cutout":0,"useOneColor":false,"useUTC":false,"colors":["#1f77b4","#aec7e8","#ff7f0e","#2ca02c","#98df8a","#d62728","#ff9896","#9467bd","#c5b0d5"],"outputs":1,"useDifferentColor":false,"x":1170,"y":440,"wires":[[]]},{"id":"6ad9b03.1f9965","type":"ui_group","name":"Últimos tweets","tab":"855ca468.adf328","order":1,"disp":true,"width":28,"collapse":false},{"id":"855ca468.adf328","type":"ui_tab","name":"Categoria mas mencionada (Comida, Tecnología o Deportes)","icon":"dashboard","disabled":false,"hidden":false}]